begin_compilation
  name " test.output.HelloWorldReflect::main"
  method "static void test.output.HelloWorldReflect.main(String[])"
  date 1588016544982
end_compilation
begin_cfg
  name "T1X static void test.output.HelloWorldReflect.main(java.lang.String[])"
end_cfg
begin_nmethod
  ;; ------ Exception Handlers ------
  ;;     java.lang.Exception @ [83 .. 854) -> 905
  0x4002B350   0000          jmp       L1: +8                                   [E9 08 00 00 00]
  0x4002B355   0005          nop                                                [90]
  0x4002B356   0006          nop                                                [90]
  0x4002B357   0007          nop                                                [90]
  0x4002B358   0008          call      L1: +0 OPT2BASELINE-Adapter(R)           [E8 00 00 00 00]
  ;; reg-ref-map: {}
  ;; frame-ref-map: {}
  ;; at test.output.HelloWorldReflect.main(String[]) [bci: -1]
  ;;             |0           |1           |2           |3          
  ;;    locals:  |[rbp+80]:j  |[rbp-16]:j  |[rbp-32]:j  |           
  ;;    stack:   |[rbp-48]:j  |[rbp-64]:j  |[rbp-80]:j  |[rbp-96]:j
  0x4002B35D   0013   L1 :   enter     0x60, 0x0                                [C8 60 00 00]
  0x4002B361   0017          subq      rbp, 0x40                                [48 83 ED 40]
  0x4002B365   0021          mov       [rsp - 8088], rax                        [48 89 84 24 68 E0 FF FF]
  0x4002B36D   0029          xor       r11, r11                                 [4D 33 DB]
  0x4002B370   0032          mov       [-167], r11                              [4C 89 1D 59 FF FF FF]
  0x4002B377   0039          mov       rdi, [-166]                              [48 8B 3D 5A FF FF FF]
  ;; reg-ref-map: rdi {7}
  ;; frame-ref-map: rbp+80 {22}
  ;; at test.output.HelloWorldReflect.main(String[]) [bci: -1]
  ;;             |0           |1           |2           |3          
  ;;    locals:  |[rbp+80]:a  |[rbp-16]:j  |[rbp-32]:j  |           
  ;;    stack:   |[rbp-48]:j  |[rbp-64]:j  |[rbp-80]:j  |[rbp-96]:j
  0x4002B37E   0046          movsxd    rsi, [rdi + 48]                          [48 63 77 30]
  0x4002B382   0050          subl      esi, 0x1                                 [83 EE 01]
  0x4002B385   0053          .byte 0x40                                         [40]
  0x4002B386   0054          mov       [rdi + 48], esi                          [89 77 30]
  0x4002B389   0057          cmpl      esi, 0x0                                 [83 FE 00]
  0x4002B38C   0060          jnle      L3: +17                                  [0F 8F 11 00 00 00]
  0x4002B392   0066          mov       rsi, 0x0                                 [48 BE 00 00 00 00 00 00 00 00]
  0x4002B39C   0076          nop                                                [90]
  0x4002B39D   0077          call      L2: +0 com.sun.max.vm.compiler.CompilationBroker.instrumentationCounterOverflow(MethodProfile, Object)   [E8 00 00 00 00]
  ;; reg-ref-map: {}
  ;; frame-ref-map: rbp+80 {22}
  ;; at test.output.HelloWorldReflect.main(String[]) [bci: -1]
  ;;             |0           |1           |2           |3          
  ;;    locals:  |[rbp+80]:a  |[rbp-16]:j  |[rbp-32]:j  |           
  ;;    stack:   |[rbp-48]:j  |[rbp-64]:j  |[rbp-80]:j  |[rbp-96]:j
  0x4002B3A2   0082   L2 :   nop                                                [90]
  ;; -------------------- 0: ldc 2 ----------------------------------------------------------------------
  0x4002B3A3   0083   L3 :   subq      rsp, 0x10                                [48 83 EC 10]
  0x4002B3A7   0087          mov       r11, [-206]                              [4C 8B 1D 32 FF FF FF]
  0x4002B3AE   0094          mov       [rsp], r11                               [4C 89 1C 24]
  ;; -------------------- 2: invokevirtual 0 3 ----------------------------------------------------------
  0x4002B3B2   0098          mov       r11, [rsp]                               [4C 8B 1C 24]
  0x4002B3B6   0102          test      [r11], eax                               [41 85 03]
  0x4002B3B9   0105          mov       rdi, [rsp]                               [48 8B 3C 24]
  0x4002B3BD   0109          nop                                                [90]
  0x4002B3BE   0110          nop                                                [90]
  0x4002B3BF   0111          nop                                                [90]
  0x4002B3C0   0112          call      L4: +0 java.lang.Class.getClassLoader()   [E8 00 00 00 00]
  ;; reg-ref-map: {}
  ;; frame-ref-map: rbp+80 {22}
  ;; at test.output.HelloWorldReflect.main(HelloWorldReflect.java:35) [bci: 2]
  ;;             |0           |1           |2           |3          
  ;;    locals:  |[rbp+80]:a  |[rbp-16]:j  |[rbp-32]:j  |           
  ;;    stack:   |[rbp-48]:j  |[rbp-64]:j  |[rbp-80]:j  |[rbp-96]:j
  0x4002B3C5   0117   L4 :   nop                                                [90]
  0x4002B3C6   0118          subq      rsp, 0x10                                [48 83 EC 10]
  0x4002B3CA   0122          mov       [rsp], rax                               [48 89 04 24]
  ;; -------------------- 5: astore_1 -------------------------------------------------------------------
  0x4002B3CE   0126          mov       r11, [rsp]                               [4C 8B 1C 24]
  0x4002B3D2   0130          addq      rsp, 0x10                                [48 83 C4 10]
  0x4002B3D6   0134          mov       [rbp - 16], r11                          [4C 89 5D F0]
  ;; -------------------- 6: invokestatic 0 4 -----------------------------------------------------------
  0x4002B3DA   0138          call      L5: +0 java.lang.ClassLoader.getSystemClassLoader()   [E8 00 00 00 00]
  ;; reg-ref-map: {}
  ;; frame-ref-map: rbp-16 rbp+80 {10, 22}
  ;; at test.output.HelloWorldReflect.main(HelloWorldReflect.java:36) [bci: 6]
  ;;             |0           |1           |2           |3          
  ;;    locals:  |[rbp+80]:a  |[rbp-16]:a  |[rbp-32]:j  |           
  ;;    stack:   |[rbp-48]:j  |[rbp-64]:j  |[rbp-80]:j  |[rbp-96]:j
  0x4002B3DF   0143   L5 :   nop                                                [90]
  0x4002B3E0   0144          subq      rsp, 0x10                                [48 83 EC 10]
  0x4002B3E4   0148          mov       [rsp], rax                               [48 89 04 24]
  ;; -------------------- 9: astore_2 -------------------------------------------------------------------
  0x4002B3E8   0152          mov       r11, [rsp]                               [4C 8B 1C 24]
  0x4002B3EC   0156          addq      rsp, 0x10                                [48 83 C4 10]
  0x4002B3F0   0160          mov       [rbp - 32], r11                          [4C 89 5D E0]
  ;; -------------------- 10: getstatic 0 5 -------------------------------------------------------------
  0x4002B3F4   0164          mov       rdi, [-275]                              [48 8B 3D ED FE FF FF]
  0x4002B3FB   0171          mov       esi, 0x18                                [BE 18 00 00 00]
  0x4002B400   0176          movsxd    rsi, esi                                 [48 63 F6]
  ;; reg-ref-map: {}
  ;; frame-ref-map: rbp-32 rbp-16 rbp+80 {8, 10, 22}
  ;; at test.output.HelloWorldReflect.main(HelloWorldReflect.java:38) [bci: 10]
  ;;             |0           |1           |2           |3          
  ;;    locals:  |[rbp+80]:a  |[rbp-16]:a  |[rbp-32]:a  |           
  ;;    stack:   |[rbp-48]:j  |[rbp-64]:j  |[rbp-80]:j  |[rbp-96]:j
  0x4002B403   0179          mov       rax, rdi[rsi]                            [48 8B 04 37]
  0x4002B407   0183          subq      rsp, 0x10                                [48 83 EC 10]
  0x4002B40B   0187          mov       [rsp], rax                               [48 89 04 24]
  ;; -------------------- 13: new 0 6 -------------------------------------------------------------------
  0x4002B40F   0191          mov       rdi, [-294]                              [48 8B 3D DA FE FF FF]
  0x4002B416   0198          mov       [rbp + 8], rdi                           [48 89 7D 08]
  0x4002B41A   0202          mov       rsi, [-297]                              [48 8B 35 D7 FE FF FF]
  ;; reg-ref-map: rsi rdi {6, 7}
  ;; frame-ref-map: rbp-48 rbp-32 rbp-16 rbp+8 rbp+80 {6, 8, 10, 13, 22}
  ;; at test.output.HelloWorldReflect.main(HelloWorldReflect.java:38) [bci: 13]
  ;;             |0           |1           |2           |3          
  ;;    locals:  |[rbp+80]:a  |[rbp-16]:a  |[rbp-32]:a  |           
  ;;    stack:   |[rbp-48]:a  |[rbp-64]:j  |[rbp-80]:j  |[rbp-96]:j
  0x4002B421   0209          mov       rdx, [rdi + 24]                          [48 8B 57 18]
  0x4002B425   0213          mov       rcx, r14                                 [49 8B CE]
  0x4002B428   0216          mov       rax, [rcx + 8]                           [48 8B 41 08]
  ;; reg-ref-map: rsi rdi {6, 7}
  ;; frame-ref-map: rbp-48 rbp-32 rbp-16 rbp+8 rbp+80 {6, 8, 10, 13, 22}
  ;; at test.output.HelloWorldReflect.main(HelloWorldReflect.java:38) [bci: 13]
  ;;             |0           |1           |2           |3          
  ;;    locals:  |[rbp+80]:a  |[rbp-16]:a  |[rbp-32]:a  |           
  ;;    stack:   |[rbp-48]:a  |[rbp-64]:j  |[rbp-80]:j  |[rbp-96]:j
  0x4002B42C   0220          mov       rcx, [rax + 296]                         [48 8B 88 28 01 00 00]
  0x4002B433   0227          mov       r8, [rax + 288]                          [4C 8B 80 20 01 00 00]
  0x4002B43A   0234          mov       rbx, rcx                                 [48 8B D9]
  0x4002B43D   0237          add       rbx, rdx                                 [48 03 DA]
  0x4002B440   0240          mov       r9, rbx                                  [4C 8B CB]
  0x4002B443   0243          cmp       r9, r8                                   [4D 3B C8]
  0x4002B446   0246          jbe       L7: +20                                  [0F 86 14 00 00 00]
  0x4002B44C   0252          mov       rdi, rsi                                 [48 8B FE]
  0x4002B44F   0255          mov       rsi, rdx                                 [48 8B F2]
  0x4002B452   0258          mov       rdx, rax                                 [48 8B D0]
  0x4002B455   0261          call      L6: +0 com.sun.max.vm.heap.HeapSchemeWithTLAB.slowPathAllocate(Size, Pointer, Pointer, Pointer)   [E8 00 00 00 00]
  ;; reg-ref-map: {}
  ;; frame-ref-map: rbp-48 rbp-32 rbp-16 rbp+8 rbp+80 {6, 8, 10, 13, 22}
  ;; at test.output.HelloWorldReflect.main(HelloWorldReflect.java:38) [bci: 13]
  ;;             |0           |1           |2           |3          
  ;;    locals:  |[rbp+80]:a  |[rbp-16]:a  |[rbp-32]:a  |           
  ;;    stack:   |[rbp-48]:a  |[rbp-64]:j  |[rbp-80]:j  |[rbp-96]:j
  0x4002B45A   0266   L6 :   nop                                                [90]
  0x4002B45B   0267          jmp       L8: +10                                  [E9 0A 00 00 00]
  0x4002B460   0272   L7 :   mov       [rax + 296], rbx                         [48 89 98 28 01 00 00]
  0x4002B467   0279          mov       rax, rcx                                 [48 8B C1]
  0x4002B46A   0282   L8 :   mov       [rbp + 16], rax                          [48 89 45 10]
  0x4002B46E   0286          mov       rdi, [rbp + 8]                           [48 8B 7D 08]
  0x4002B472   0290          nop                                                [90]
  0x4002B473   0291          nop                                                [90]
  0x4002B474   0292          nop                                                [90]
  0x4002B475   0293          call      L9: +0 com.sun.max.vm.profilers.tracing.numa.NUMAProfiler.checkForFlareObject(Hub)   [E8 00 00 00 00]
  ;; reg-ref-map: {}
  ;; frame-ref-map: rbp-48 rbp-32 rbp-16 rbp+8 rbp+80 {6, 8, 10, 13, 22}
  ;; at test.output.HelloWorldReflect.main(HelloWorldReflect.java:38) [bci: 13]
  ;;             |0           |1           |2           |3          
  ;;    locals:  |[rbp+80]:a  |[rbp-16]:a  |[rbp-32]:a  |           
  ;;    stack:   |[rbp-48]:a  |[rbp-64]:j  |[rbp-80]:j  |[rbp-96]:j
  0x4002B47A   0298   L9 :   nop                                                [90]
  0x4002B47B   0299          nop                                                [90]
  0x4002B47C   0300          nop                                                [90]
  0x4002B47D   0301          call      L10: +0 com.sun.max.vm.profilers.tracing.numa.NUMAProfiler.shouldProfile()   [E8 00 00 00 00]
  ;; reg-ref-map: {}
  ;; frame-ref-map: rbp-48 rbp-32 rbp-16 rbp+8 rbp+80 {6, 8, 10, 13, 22}
  ;; at test.output.HelloWorldReflect.main(HelloWorldReflect.java:38) [bci: 13]
  ;;             |0           |1           |2           |3          
  ;;    locals:  |[rbp+80]:a  |[rbp-16]:a  |[rbp-32]:a  |           
  ;;    stack:   |[rbp-48]:a  |[rbp-64]:j  |[rbp-80]:j  |[rbp-96]:j
  0x4002B482   0306   L10:   nop                                                [90]
  0x4002B483   0307          cmpl      eax, 0x0                                 [83 F8 00]
  0x4002B486   0310          jz        L12: +39                                 [0F 84 27 00 00 00]
  0x4002B48C   0316          mov       rdi, [rbp + 8]                           [48 8B 7D 08]
  0x4002B490   0320          mov       rsi, [rdi + 48]                          [48 8B 77 30]
  ;; reg-ref-map: rsi rdi {6, 7}
  ;; frame-ref-map: rbp-48 rbp-32 rbp-16 rbp+8 rbp+80 {6, 8, 10, 13, 22}
  ;; at test.output.HelloWorldReflect.main(HelloWorldReflect.java:38) [bci: 13]
  ;;             |0           |1           |2           |3          
  ;;    locals:  |[rbp+80]:a  |[rbp-16]:a  |[rbp-32]:a  |           
  ;;    stack:   |[rbp-48]:a  |[rbp-64]:j  |[rbp-80]:j  |[rbp-96]:j
  0x4002B494   0324          test      [rsi], eax                               [85 06]
  0x4002B496   0326          mov       rdx, [rsi + 40]                          [48 8B 56 28]
  ;; reg-ref-map: rdx rdi {2, 7}
  ;; frame-ref-map: rbp-48 rbp-32 rbp-16 rbp+8 rbp+80 {6, 8, 10, 13, 22}
  ;; at test.output.HelloWorldReflect.main(HelloWorldReflect.java:38) [bci: 13]
  ;;             |0           |1           |2           |3          
  ;;    locals:  |[rbp+80]:a  |[rbp-16]:a  |[rbp-32]:a  |           
  ;;    stack:   |[rbp-48]:a  |[rbp-64]:j  |[rbp-80]:j  |[rbp-96]:j
  0x4002B49A   0330          mov       rsi, [rdx + 16]                          [48 8B 72 10]
  0x4002B49E   0334          mov       rdx, [rdi + 24]                          [48 8B 57 18]
  0x4002B4A2   0338          andl      edx, 0xFF                                [83 E2 FF]
  0x4002B4A5   0341          mov       rdi, rdx                                 [48 8B FA]
  0x4002B4A8   0344          mov       rdx, [rbp + 16]                          [48 8B 55 10]
  0x4002B4AC   0348          nop                                                [90]
  0x4002B4AD   0349          call      L11: +0 com.sun.max.vm.profilers.tracing.numa.NUMAProfiler.profileNew(int, String, long)   [E8 00 00 00 00]
  ;; reg-ref-map: {}
  ;; frame-ref-map: rbp-48 rbp-32 rbp-16 rbp+8 rbp+80 {6, 8, 10, 13, 22}
  ;; at test.output.HelloWorldReflect.main(HelloWorldReflect.java:38) [bci: 13]
  ;;             |0           |1           |2           |3          
  ;;    locals:  |[rbp+80]:a  |[rbp-16]:a  |[rbp-32]:a  |           
  ;;    stack:   |[rbp-48]:a  |[rbp-64]:j  |[rbp-80]:j  |[rbp-96]:j
  0x4002B4B2   0354   L11:   nop                                                [90]
  0x4002B4B3   0355   L12:   mov       rax, [rbp + 16]                          [48 8B 45 10]
  0x4002B4B7   0359          mov       rdi, [rbp + 8]                           [48 8B 7D 08]
  ;; reg-ref-map: {}
  ;; frame-ref-map: rbp-48 rbp-32 rbp-16 rbp+80 {6, 8, 10, 22}
  ;; at test.output.HelloWorldReflect.main(HelloWorldReflect.java:38) [bci: 13]
  ;;             |0           |1           |2           |3          
  ;;    locals:  |[rbp+80]:a  |[rbp-16]:a  |[rbp-32]:a  |           
  ;;    stack:   |[rbp-48]:a  |[rbp-64]:j  |[rbp-80]:j  |[rbp-96]:j
  0x4002B4BB   0363          mov       [rax], rdi                               [48 89 38]
  0x4002B4BE   0366          subq      rsp, 0x10                                [48 83 EC 10]
  0x4002B4C2   0370          mov       [rsp], rax                               [48 89 04 24]
  ;; -------------------- 16: dup -----------------------------------------------------------------------
  0x4002B4C6   0374          subq      rsp, 0x10                                [48 83 EC 10]
  0x4002B4CA   0378          mov       r11, [rsp + 16]                          [4C 8B 5C 24 10]
  0x4002B4CF   0383          mov       [rsp], r11                               [4C 89 1C 24]
  ;; -------------------- 17: invokespecial 0 7 ---------------------------------------------------------
  0x4002B4D3   0387          mov       r11, [rsp]                               [4C 8B 1C 24]
  0x4002B4D7   0391          test      [r11], eax                               [41 85 03]
  0x4002B4DA   0394          call      L13: +0 java.lang.StringBuilder.<init>()   [E8 00 00 00 00]
  ;; reg-ref-map: {}
  ;; frame-ref-map: rbp-64 rbp-48 rbp-32 rbp-16 rbp+80 {4, 6, 8, 10, 22}
  ;; at test.output.HelloWorldReflect.main(HelloWorldReflect.java:38) [bci: 17]
  ;;             |0           |1           |2           |3          
  ;;    locals:  |[rbp+80]:a  |[rbp-16]:a  |[rbp-32]:a  |           
  ;;    stack:   |[rbp-48]:a  |[rbp-64]:a  |[rbp-80]:j  |[rbp-96]:j
  0x4002B4DF   0399   L13:   nop                                                [90]
  ;; -------------------- 20: ldc 8 ---------------------------------------------------------------------
  0x4002B4E0   0400          mov       r11, [-487]                              [4C 8B 1D 19 FE FF FF]
  0x4002B4E7   0407          subq      rsp, 0x10                                [48 83 EC 10]
  0x4002B4EB   0411          mov       [rsp], r11                               [4C 89 1C 24]
  ;; -------------------- 22: invokevirtual 0 9 ---------------------------------------------------------
  0x4002B4EF   0415          mov       r11, [rsp + 16]                          [4C 8B 5C 24 10]
  0x4002B4F4   0420          test      [r11], eax                               [41 85 03]
  0x4002B4F7   0423          mov       rdi, [rsp + 16]                          [48 8B 7C 24 10]
  0x4002B4FC   0428          nop                                                [90]
  0x4002B4FD   0429          nop                                                [90]
  0x4002B4FE   0430          nop                                                [90]
  0x4002B4FF   0431          nop                                                [90]
  0x4002B500   0432          call      L14: +0 java.lang.StringBuilder.append(String)   [E8 00 00 00 00]
  ;; reg-ref-map: {}
  ;; frame-ref-map: rbp-48 rbp-32 rbp-16 rbp+80 {6, 8, 10, 22}
  ;; at test.output.HelloWorldReflect.main(HelloWorldReflect.java:38) [bci: 22]
  ;;             |0           |1           |2           |3          
  ;;    locals:  |[rbp+80]:a  |[rbp-16]:a  |[rbp-32]:a  |           
  ;;    stack:   |[rbp-48]:a  |[rbp-64]:j  |[rbp-80]:j  |[rbp-96]:j
  0x4002B505   0437   L14:   nop                                                [90]
  0x4002B506   0438          subq      rsp, 0x10                                [48 83 EC 10]
  0x4002B50A   0442          mov       [rsp], rax                               [48 89 04 24]
  ;; -------------------- 25: aload_1 -------------------------------------------------------------------
  0x4002B50E   0446          mov       r11, [rbp - 16]                          [4C 8B 5D F0]
  0x4002B512   0450          subq      rsp, 0x10                                [48 83 EC 10]
  0x4002B516   0454          mov       [rsp], r11                               [4C 89 1C 24]
  ;; -------------------- 26: aload_2 -------------------------------------------------------------------
  0x4002B51A   0458          mov       r11, [rbp - 32]                          [4C 8B 5D E0]
  0x4002B51E   0462          subq      rsp, 0x10                                [48 83 EC 10]
  0x4002B522   0466          mov       [rsp], r11                               [4C 89 1C 24]
  ;; -------------------- 27: if_acmpne 0 7 -------------------------------------------------------------
  0x4002B526   0470          mov       r11, [rsp + 16]                          [4C 8B 5C 24 10]
  0x4002B52B   0475          mov       rax, [rsp]                               [48 8B 04 24]
  0x4002B52F   0479          addq      rsp, 0x20                                [48 83 C4 20]
  0x4002B533   0483          cmp       r11, rax                                 [4C 3B D8]
  0x4002B536   0486          jz        L16: +51                                 [74 33]
  0x4002B538   0488          mov       rdi, [-567]                              [48 8B 3D C9 FD FF FF]
  0x4002B53F   0495          mov       esi, 0x4                                 [BE 04 00 00 00]
  ;; reg-ref-map: rdi {7}
  ;; frame-ref-map: rbp-96 rbp-80 rbp-64 rbp-48 rbp-32 rbp-16 rbp+80 {0, 2, 4, 6, 8, 10, 22}
  ;; at test.output.HelloWorldReflect.main(HelloWorldReflect.java:38) [bci: 27]
  ;;             |0           |1           |2           |3          
  ;;    locals:  |[rbp+80]:a  |[rbp-16]:a  |[rbp-32]:a  |           
  ;;    stack:   |[rbp-48]:a  |[rbp-64]:a  |[rbp-80]:a  |[rbp-96]:a
  0x4002B544   0500          mov       rax, [rdi + 24]                          [48 8B 47 18]
  0x4002B548   0504          mov       rcx, rax                                 [48 8B C8]
  0x4002B54B   0507          movsxd    rsi, esi                                 [48 63 F6]
  ;; reg-ref-map: rax {0}
  ;; frame-ref-map: rbp-96 rbp-80 rbp-64 rbp-48 rbp-32 rbp-16 rbp+80 {0, 2, 4, 6, 8, 10, 22}
  ;; at test.output.HelloWorldReflect.main(HelloWorldReflect.java:38) [bci: 27]
  ;;             |0           |1           |2           |3          
  ;;    locals:  |[rbp+80]:a  |[rbp-16]:a  |[rbp-32]:a  |           
  ;;    stack:   |[rbp-48]:a  |[rbp-64]:a  |[rbp-80]:a  |[rbp-96]:a
  0x4002B54E   0510          movsxd    rcx, rcx[rsi * 4 + 24]                   [48 63 4C B1 18]
  0x4002B553   0515          cmpl      ecx, 0x7FFFFFFF                          [81 F9 FF FF FF 7F]
  0x4002B559   0521          jnl       L15: +7                                  [0F 8D 07 00 00 00]
  0x4002B55F   0527          addl      ecx, 0x1                                 [83 C1 01]
  0x4002B562   0530          mov       rax[rsi * 4 + 24], ecx                   [89 4C B0 18]
  0x4002B566   0534   L15:   jmp       L19: +111                                [E9 6F 00 00 00]
  0x4002B56B   0539   L16:   mov       rdi, [-610]                              [48 8B 3D 9E FD FF FF]
  0x4002B572   0546          mov       esi, 0x5                                 [BE 05 00 00 00]
  ;; reg-ref-map: rdi {7}
  ;; frame-ref-map: rbp-96 rbp-80 rbp-64 rbp-48 rbp-32 rbp-16 rbp+80 {0, 2, 4, 6, 8, 10, 22}
  ;; at test.output.HelloWorldReflect.main(HelloWorldReflect.java:38) [bci: 27]
  ;;             |0           |1           |2           |3          
  ;;    locals:  |[rbp+80]:a  |[rbp-16]:a  |[rbp-32]:a  |           
  ;;    stack:   |[rbp-48]:a  |[rbp-64]:a  |[rbp-80]:a  |[rbp-96]:a
  0x4002B577   0551          mov       rax, [rdi + 24]                          [48 8B 47 18]
  0x4002B57B   0555          mov       rcx, rax                                 [48 8B C8]
  0x4002B57E   0558          movsxd    rsi, esi                                 [48 63 F6]
  ;; reg-ref-map: rax {0}
  ;; frame-ref-map: rbp-96 rbp-80 rbp-64 rbp-48 rbp-32 rbp-16 rbp+80 {0, 2, 4, 6, 8, 10, 22}
  ;; at test.output.HelloWorldReflect.main(HelloWorldReflect.java:38) [bci: 27]
  ;;             |0           |1           |2           |3          
  ;;    locals:  |[rbp+80]:a  |[rbp-16]:a  |[rbp-32]:a  |           
  ;;    stack:   |[rbp-48]:a  |[rbp-64]:a  |[rbp-80]:a  |[rbp-96]:a
  0x4002B581   0561          movsxd    rcx, rcx[rsi * 4 + 24]                   [48 63 4C B1 18]
  0x4002B586   0566          cmpl      ecx, 0x7FFFFFFF                          [81 F9 FF FF FF 7F]
  0x4002B58C   0572          jnl       L17: +7                                  [0F 8D 07 00 00 00]
  0x4002B592   0578          addl      ecx, 0x1                                 [83 C1 01]
  0x4002B595   0581          mov       rax[rsi * 4 + 24], ecx                   [89 4C B0 18]
  ;; -------------------- 30: iconst_1 ------------------------------------------------------------------
  0x4002B599   0585   L17:   mov       r11d, 0x1                                [41 BB 01 00 00 00]
  0x4002B59F   0591          subq      rsp, 0x10                                [48 83 EC 10]
  0x4002B5A3   0595          mov       [rsp], r11d                              [44 89 1C 24]
  ;; -------------------- 31: goto 0 4 ------------------------------------------------------------------
  0x4002B5A7   0599          mov       rdi, [-662]                              [48 8B 3D 6A FD FF FF]
  0x4002B5AE   0606          mov       esi, 0x6                                 [BE 06 00 00 00]
  ;; reg-ref-map: rdi {7}
  ;; frame-ref-map: rbp-64 rbp-48 rbp-32 rbp-16 rbp+80 {4, 6, 8, 10, 22}
  ;; at test.output.HelloWorldReflect.main(HelloWorldReflect.java:38) [bci: 31]
  ;;             |0           |1           |2           |3          
  ;;    locals:  |[rbp+80]:a  |[rbp-16]:a  |[rbp-32]:a  |           
  ;;    stack:   |[rbp-48]:a  |[rbp-64]:a  |[rbp-80]:j  |[rbp-96]:j
  0x4002B5B3   0611          mov       rax, [rdi + 24]                          [48 8B 47 18]
  0x4002B5B7   0615          mov       rcx, rax                                 [48 8B C8]
  0x4002B5BA   0618          movsxd    rsi, esi                                 [48 63 F6]
  ;; reg-ref-map: rax {0}
  ;; frame-ref-map: rbp-64 rbp-48 rbp-32 rbp-16 rbp+80 {4, 6, 8, 10, 22}
  ;; at test.output.HelloWorldReflect.main(HelloWorldReflect.java:38) [bci: 31]
  ;;             |0           |1           |2           |3          
  ;;    locals:  |[rbp+80]:a  |[rbp-16]:a  |[rbp-32]:a  |           
  ;;    stack:   |[rbp-48]:a  |[rbp-64]:a  |[rbp-80]:j  |[rbp-96]:j
  0x4002B5BD   0621          movsxd    rcx, rcx[rsi * 4 + 24]                   [48 63 4C B1 18]
  0x4002B5C2   0626          cmpl      ecx, 0x7FFFFFFF                          [81 F9 FF FF FF 7F]
  0x4002B5C8   0632          jnl       L18: +7                                  [0F 8D 07 00 00 00]
  0x4002B5CE   0638          addl      ecx, 0x1                                 [83 C1 01]
  0x4002B5D1   0641          mov       rax[rsi * 4 + 24], ecx                   [89 4C B0 18]
  0x4002B5D5   0645   L18:   jmp       L20: +14                                 [E9 0E 00 00 00]
  ;; -------------------- 34: iconst_0 ------------------------------------------------------------------
  0x4002B5DA   0650   L19:   mov       r11d, 0x0                                [41 BB 00 00 00 00]
  0x4002B5E0   0656          subq      rsp, 0x10                                [48 83 EC 10]
  0x4002B5E4   0660          mov       [rsp], r11d                              [44 89 1C 24]
  ;; -------------------- 35: invokevirtual 0 10 --------------------------------------------------------
  0x4002B5E8   0664   L20:   mov       r11, [rsp + 16]                          [4C 8B 5C 24 10]
  0x4002B5ED   0669          test      [r11], eax                               [41 85 03]
  0x4002B5F0   0672          mov       rdi, [rsp + 16]                          [48 8B 7C 24 10]
  0x4002B5F5   0677          nop                                                [90]
  0x4002B5F6   0678          nop                                                [90]
  0x4002B5F7   0679          nop                                                [90]
  0x4002B5F8   0680          call      L21: +0 java.lang.StringBuilder.append(boolean)   [E8 00 00 00 00]
  ;; reg-ref-map: {}
  ;; frame-ref-map: rbp-48 rbp-32 rbp-16 rbp+80 {6, 8, 10, 22}
  ;; at test.output.HelloWorldReflect.main(HelloWorldReflect.java:38) [bci: 35]
  ;;             |0           |1           |2           |3          
  ;;    locals:  |[rbp+80]:a  |[rbp-16]:a  |[rbp-32]:a  |           
  ;;    stack:   |[rbp-48]:a  |[rbp-64]:j  |[rbp-80]:j  |[rbp-96]:j
  0x4002B5FD   0685   L21:   nop                                                [90]
  0x4002B5FE   0686          subq      rsp, 0x10                                [48 83 EC 10]
  0x4002B602   0690          mov       [rsp], rax                               [48 89 04 24]
  ;; -------------------- 38: invokevirtual 0 11 --------------------------------------------------------
  0x4002B606   0694          mov       r11, [rsp]                               [4C 8B 1C 24]
  0x4002B60A   0698          test      [r11], eax                               [41 85 03]
  0x4002B60D   0701          mov       rdi, [rsp]                               [48 8B 3C 24]
  0x4002B611   0705          call      L22: +0 java.lang.StringBuilder.toString()   [E8 00 00 00 00]
  ;; reg-ref-map: {}
  ;; frame-ref-map: rbp-48 rbp-32 rbp-16 rbp+80 {6, 8, 10, 22}
  ;; at test.output.HelloWorldReflect.main(HelloWorldReflect.java:38) [bci: 38]
  ;;             |0           |1           |2           |3          
  ;;    locals:  |[rbp+80]:a  |[rbp-16]:a  |[rbp-32]:a  |           
  ;;    stack:   |[rbp-48]:a  |[rbp-64]:j  |[rbp-80]:j  |[rbp-96]:j
  0x4002B616   0710   L22:   nop                                                [90]
  0x4002B617   0711          subq      rsp, 0x10                                [48 83 EC 10]
  0x4002B61B   0715          mov       [rsp], rax                               [48 89 04 24]
  ;; -------------------- 41: invokevirtual 0 12 --------------------------------------------------------
  0x4002B61F   0719          mov       edi, 0x2F                                [BF 2F 00 00 00]
  0x4002B624   0724          mov       rsi, [rsp + 16]                          [48 8B 74 24 10]
  0x4002B629   0729          mov       rdx, [-784]                              [48 8B 15 F0 FC FF FF]
  0x4002B630   0736          mov       ecx, 0xA                                 [B9 0A 00 00 00]
  0x4002B635   0741          mov       rax, rsi                                 [48 8B C6]
  ;; reg-ref-map: rdx rsi {2, 6}
  ;; frame-ref-map: rbp-64 rbp-48 rbp-32 rbp-16 rbp+80 {4, 6, 8, 10, 22}
  ;; at test.output.HelloWorldReflect.main(HelloWorldReflect.java:38) [bci: 41]
  ;;             |0           |1           |2           |3          
  ;;    locals:  |[rbp+80]:a  |[rbp-16]:a  |[rbp-32]:a  |           
  ;;    stack:   |[rbp-48]:a  |[rbp-64]:a  |[rbp-80]:j  |[rbp-96]:j
  0x4002B638   0744          mov       rax, [rax]                               [48 8B 00]
  0x4002B63B   0747          movsxd    rdi, edi                                 [48 63 FF]
  ;; reg-ref-map: rdx rsi {2, 6}
  ;; frame-ref-map: rbp-64 rbp-48 rbp-32 rbp-16 rbp+80 {4, 6, 8, 10, 22}
  ;; at test.output.HelloWorldReflect.main(HelloWorldReflect.java:38) [bci: 41]
  ;;             |0           |1           |2           |3          
  ;;    locals:  |[rbp+80]:a  |[rbp-16]:a  |[rbp-32]:a  |           
  ;;    stack:   |[rbp-48]:a  |[rbp-64]:a  |[rbp-80]:j  |[rbp-96]:j
  0x4002B63E   0750          mov       rax, rax[rdi * 8 + 24]                   [48 8B 44 F8 18]
  0x4002B643   0755          mov       rdi, rdx                                 [48 8B FA]
  0x4002B646   0758          mov       rdx, rcx                                 [48 8B D1]
  0x4002B649   0761          mov       ecx, 0x3                                 [B9 03 00 00 00]
  0x4002B64E   0766          mov       [rbp + 8], rax                           [48 89 45 08]
  0x4002B652   0770          nop                                                [90]
  0x4002B653   0771          nop                                                [90]
  0x4002B654   0772          call      L23: +0 com.sun.max.vm.profile.MethodInstrumentation.recordType(MethodProfile, Object, int, int)   [E8 00 00 00 00]
  ;; reg-ref-map: {}
  ;; frame-ref-map: rbp-64 rbp-48 rbp-32 rbp-16 rbp+80 {4, 6, 8, 10, 22}
  ;; at test.output.HelloWorldReflect.main(HelloWorldReflect.java:38) [bci: 41]
  ;;             |0           |1           |2           |3          
  ;;    locals:  |[rbp+80]:a  |[rbp-16]:a  |[rbp-32]:a  |           
  ;;    stack:   |[rbp-48]:a  |[rbp-64]:a  |[rbp-80]:j  |[rbp-96]:j
  0x4002B659   0777   L23:   nop                                                [90]
  0x4002B65A   0778          mov       rax, [rbp + 8]                           [48 8B 45 08]
  0x4002B65E   0782          addq      rax, 0xF8                                [48 83 C0 F8]
  0x4002B662   0786          mov       rdi, [rsp + 16]                          [48 8B 7C 24 10]
  0x4002B667   0791          call      rax <template_call>                      [FF D0]
  ;; reg-ref-map: {}
  ;; frame-ref-map: rbp-32 rbp-16 rbp+80 {8, 10, 22}
  ;; at test.output.HelloWorldReflect.main(HelloWorldReflect.java:38) [bci: 41]
  ;;             |0           |1           |2           |3          
  ;;    locals:  |[rbp+80]:a  |[rbp-16]:a  |[rbp-32]:a  |           
  ;;    stack:   |[rbp-48]:j  |[rbp-64]:j  |[rbp-80]:j  |[rbp-96]:j
  0x4002B669   0793          nop                                                [90]
  ;; -------------------- 44: aload_0 -------------------------------------------------------------------
  0x4002B66A   0794          mov       r11, [rbp + 80]                          [4C 8B 5D 50]
  0x4002B66E   0798          subq      rsp, 0x10                                [48 83 EC 10]
  0x4002B672   0802          mov       [rsp], r11                               [4C 89 1C 24]
  ;; -------------------- 45: aload_1 -------------------------------------------------------------------
  0x4002B676   0806          mov       r11, [rbp - 16]                          [4C 8B 5D F0]
  0x4002B67A   0810          subq      rsp, 0x10                                [48 83 EC 10]
  0x4002B67E   0814          mov       [rsp], r11                               [4C 89 1C 24]
  ;; -------------------- 46: invokestatic 0 13 ---------------------------------------------------------
  0x4002B682   0818          call      L24: +0 test.output.HelloWorldReflect.invokeHellos(String[], ClassLoader)   [E8 00 00 00 00]
  ;; reg-ref-map: {}
  ;; frame-ref-map: rbp-32 rbp-16 rbp+80 {8, 10, 22}
  ;; at test.output.HelloWorldReflect.main(HelloWorldReflect.java:40) [bci: 46]
  ;;             |0           |1           |2           |3          
  ;;    locals:  |[rbp+80]:a  |[rbp-16]:a  |[rbp-32]:a  |           
  ;;    stack:   |[rbp-48]:j  |[rbp-64]:j  |[rbp-80]:j  |[rbp-96]:j
  0x4002B687   0823   L24:   nop                                                [90]
  ;; -------------------- 49: aload_0 -------------------------------------------------------------------
  0x4002B688   0824          mov       r11, [rbp + 80]                          [4C 8B 5D 50]
  0x4002B68C   0828          subq      rsp, 0x10                                [48 83 EC 10]
  0x4002B690   0832          mov       [rsp], r11                               [4C 89 1C 24]
  ;; -------------------- 50: aload_2 -------------------------------------------------------------------
  0x4002B694   0836          mov       r11, [rbp - 32]                          [4C 8B 5D E0]
  0x4002B698   0840          subq      rsp, 0x10                                [48 83 EC 10]
  0x4002B69C   0844          mov       [rsp], r11                               [4C 89 1C 24]
  ;; -------------------- 51: invokestatic 0 13 ---------------------------------------------------------
  0x4002B6A0   0848          call      L25: +0 test.output.HelloWorldReflect.invokeHellos(String[], ClassLoader)   [E8 00 00 00 00]
  ;; reg-ref-map: {}
  ;; frame-ref-map: rbp-32 rbp-16 rbp+80 {8, 10, 22}
  ;; at test.output.HelloWorldReflect.main(HelloWorldReflect.java:41) [bci: 51]
  ;;             |0           |1           |2           |3          
  ;;    locals:  |[rbp+80]:a  |[rbp-16]:a  |[rbp-32]:a  |           
  ;;    stack:   |[rbp-48]:j  |[rbp-64]:j  |[rbp-80]:j  |[rbp-96]:j
  0x4002B6A5   0853   L25:   nop                                                [90]
  ;; -------------------- 54: goto 0 8 ------------------------------------------------------------------
  0x4002B6A6   0854          mov       rdi, [-901]                              [48 8B 3D 7B FC FF FF]
  0x4002B6AD   0861          mov       esi, 0x14                                [BE 14 00 00 00]
  ;; reg-ref-map: rdi {7}
  ;; frame-ref-map: rbp-32 rbp-16 rbp+80 {8, 10, 22}
  ;; at test.output.HelloWorldReflect.main(HelloWorldReflect.java:44) [bci: 54]
  ;;             |0           |1           |2           |3          
  ;;    locals:  |[rbp+80]:a  |[rbp-16]:a  |[rbp-32]:a  |           
  ;;    stack:   |[rbp-48]:j  |[rbp-64]:j  |[rbp-80]:j  |[rbp-96]:j
  0x4002B6B2   0866          mov       rax, [rdi + 24]                          [48 8B 47 18]
  0x4002B6B6   0870          mov       rcx, rax                                 [48 8B C8]
  0x4002B6B9   0873          movsxd    rsi, esi                                 [48 63 F6]
  ;; reg-ref-map: rax {0}
  ;; frame-ref-map: rbp-32 rbp-16 rbp+80 {8, 10, 22}
  ;; at test.output.HelloWorldReflect.main(HelloWorldReflect.java:44) [bci: 54]
  ;;             |0           |1           |2           |3          
  ;;    locals:  |[rbp+80]:a  |[rbp-16]:a  |[rbp-32]:a  |           
  ;;    stack:   |[rbp-48]:j  |[rbp-64]:j  |[rbp-80]:j  |[rbp-96]:j
  0x4002B6BC   0876          movsxd    rcx, rcx[rsi * 4 + 24]                   [48 63 4C B1 18]
  0x4002B6C1   0881          cmpl      ecx, 0x7FFFFFFF                          [81 F9 FF FF FF 7F]
  0x4002B6C7   0887          jnl       L26: +7                                  [0F 8D 07 00 00 00]
  0x4002B6CD   0893          addl      ecx, 0x1                                 [83 C1 01]
  0x4002B6D0   0896          mov       rax[rsi * 4 + 24], ecx                   [89 4C B0 18]
  0x4002B6D4   0900   L26:   jmp       L29: +120                                [E9 78 00 00 00]
  ;; -------------------- 57: astore_1 ------------------------------------------------------------------
  0x4002B6D9   0905          mov       rdi, r14                                 [49 8B FE]
  0x4002B6DC   0908          mov       rdi, [rdi + 72]                          [48 8B 7F 48]
  ;; reg-ref-map: rdi {7}
  ;; frame-ref-map: rbp-48 rbp+80 {6, 22}
  ;; at test.output.HelloWorldReflect.main(HelloWorldReflect.java:42) [bci: 57]
  ;;             |0           |1           |2           |3          
  ;;    locals:  |[rbp+80]:a  |[rbp-16]:j  |[rbp-32]:j  |           
  ;;    stack:   |[rbp-48]:a  |[rbp-64]:j  |[rbp-80]:j  |[rbp-96]:j
  0x4002B6E0   0912          test      [rdi], eax                               [85 07]
  0x4002B6E2   0914          call      L27: +0 com.sun.max.vm.thread.VmThread.loadExceptionForHandler()   [E8 00 00 00 00]
  ;; reg-ref-map: {}
  ;; frame-ref-map: rbp-48 rbp+80 {6, 22}
  ;; at test.output.HelloWorldReflect.main(HelloWorldReflect.java:42) [bci: 57]
  ;;             |0           |1           |2           |3          
  ;;    locals:  |[rbp+80]:a  |[rbp-16]:j  |[rbp-32]:j  |           
  ;;    stack:   |[rbp-48]:a  |[rbp-64]:j  |[rbp-80]:j  |[rbp-96]:j
  0x4002B6E7   0919   L27:   nop                                                [90]
  0x4002B6E8   0920          subq      rsp, 0x10                                [48 83 EC 10]
  0x4002B6EC   0924          mov       [rsp], rax                               [48 89 04 24]
  0x4002B6F0   0928          mov       r11, [rsp]                               [4C 8B 1C 24]
  0x4002B6F4   0932          addq      rsp, 0x10                                [48 83 C4 10]
  0x4002B6F8   0936          mov       [rbp - 16], r11                          [4C 89 5D F0]
  ;; -------------------- 58: aload_1 -------------------------------------------------------------------
  0x4002B6FC   0940          mov       r11, [rbp - 16]                          [4C 8B 5D F0]
  0x4002B700   0944          subq      rsp, 0x10                                [48 83 EC 10]
  0x4002B704   0948          mov       [rsp], r11                               [4C 89 1C 24]
  ;; -------------------- 59: invokevirtual 0 15 --------------------------------------------------------
  0x4002B708   0952          mov       edi, 0x1A                                [BF 1A 00 00 00]
  0x4002B70D   0957          mov       rsi, [rsp]                               [48 8B 34 24]
  0x4002B711   0961          mov       rdx, [-1000]                             [48 8B 15 18 FC FF FF]
  0x4002B718   0968          mov       ecx, 0x16                                [B9 16 00 00 00]
  0x4002B71D   0973          mov       rax, rsi                                 [48 8B C6]
  ;; reg-ref-map: rdx rsi {2, 6}
  ;; frame-ref-map: rbp-48 rbp-16 rbp+80 {6, 10, 22}
  ;; at test.output.HelloWorldReflect.main(HelloWorldReflect.java:43) [bci: 59]
  ;;             |0           |1           |2           |3          
  ;;    locals:  |[rbp+80]:a  |[rbp-16]:a  |[rbp-32]:j  |           
  ;;    stack:   |[rbp-48]:a  |[rbp-64]:j  |[rbp-80]:j  |[rbp-96]:j
  0x4002B720   0976          mov       rax, [rax]                               [48 8B 00]
  0x4002B723   0979          movsxd    rdi, edi                                 [48 63 FF]
  ;; reg-ref-map: rdx rsi {2, 6}
  ;; frame-ref-map: rbp-48 rbp-16 rbp+80 {6, 10, 22}
  ;; at test.output.HelloWorldReflect.main(HelloWorldReflect.java:43) [bci: 59]
  ;;             |0           |1           |2           |3          
  ;;    locals:  |[rbp+80]:a  |[rbp-16]:a  |[rbp-32]:j  |           
  ;;    stack:   |[rbp-48]:a  |[rbp-64]:j  |[rbp-80]:j  |[rbp-96]:j
  0x4002B726   0982          mov       rax, rax[rdi * 8 + 24]                   [48 8B 44 F8 18]
  0x4002B72B   0987          mov       rdi, rdx                                 [48 8B FA]
  0x4002B72E   0990          mov       rdx, rcx                                 [48 8B D1]
  0x4002B731   0993          mov       ecx, 0x3                                 [B9 03 00 00 00]
  0x4002B736   0998          mov       [rbp + 8], rax                           [48 89 45 08]
  0x4002B73A   1002          nop                                                [90]
  0x4002B73B   1003          nop                                                [90]
  0x4002B73C   1004          call      L28: +0 com.sun.max.vm.profile.MethodInstrumentation.recordType(MethodProfile, Object, int, int)   [E8 00 00 00 00]
  ;; reg-ref-map: {}
  ;; frame-ref-map: rbp-48 rbp-16 rbp+80 {6, 10, 22}
  ;; at test.output.HelloWorldReflect.main(HelloWorldReflect.java:43) [bci: 59]
  ;;             |0           |1           |2           |3          
  ;;    locals:  |[rbp+80]:a  |[rbp-16]:a  |[rbp-32]:j  |           
  ;;    stack:   |[rbp-48]:a  |[rbp-64]:j  |[rbp-80]:j  |[rbp-96]:j
  0x4002B741   1009   L28:   nop                                                [90]
  0x4002B742   1010          mov       rax, [rbp + 8]                           [48 8B 45 08]
  0x4002B746   1014          addq      rax, 0xF8                                [48 83 C0 F8]
  0x4002B74A   1018          mov       rdi, [rsp]                               [48 8B 3C 24]
  0x4002B74E   1022          call      rax <template_call>                      [FF D0]
  ;; reg-ref-map: {}
  ;; frame-ref-map: rbp-16 rbp+80 {10, 22}
  ;; at test.output.HelloWorldReflect.main(HelloWorldReflect.java:43) [bci: 59]
  ;;             |0           |1           |2           |3          
  ;;    locals:  |[rbp+80]:a  |[rbp-16]:a  |[rbp-32]:j  |           
  ;;    stack:   |[rbp-48]:j  |[rbp-64]:j  |[rbp-80]:j  |[rbp-96]:j
  0x4002B750   1024          nop                                                [90]
  ;; -------------------- 62: return --------------------------------------------------------------------
  0x4002B751   1025   L29:   addq      rbp, 0x40                                [48 83 C5 40]
  0x4002B755   1029          leave                                              [C9]
  0x4002B756   1030          ret       0x10                                     [C2 10 00]
   <|@
end_nmethod
begin_bytecodes
  public static void test.output.HelloWorldReflect.main(java.lang.String[])
  Stack=4, Locals=3
  [35]   0: ldc test.output.HelloWorldReflect | 18 2
  [35]   2: invokevirtual java.lang.Class.getClassLoader():ClassLoader | 182 0 3
  [35]   5: astore_1 | 76
  [36]   6: invokestatic java.lang.ClassLoader.getSystemClassLoader():ClassLoader | 184 0 4
  [36]   9: astore_2 | 77
  [38]   10: getstatic java.lang.System.out:PrintStream | 178 0 5
  [38]   13: new java.lang.StringBuilder | 187 0 6
  [38]   16: dup | 89
  [38]   17: invokespecial java.lang.StringBuilder.<init>():void | 183 0 7
  [38]   20: ldc "thisClassLoader == systemClassLoader? " | 18 8
  [38]   22: invokevirtual java.lang.StringBuilder.append(String):StringBuilder | 182 0 9
  [38]   25: aload_1 | 43
  [38]   26: aload_2 | 44
  [38]   27: if_acmpne 34 | 166 0 7
  [38]   30: iconst_1 | 4
  [38]   31: goto 35 | 167 0 4
  [38]   34: iconst_0 | 3
  [38]   35: invokevirtual java.lang.StringBuilder.append(boolean):StringBuilder | 182 0 10
  [38]   38: invokevirtual java.lang.StringBuilder.toString():String | 182 0 11
  [38]   41: invokevirtual java.io.PrintStream.println(String):void | 182 0 12
  [40]   44: aload_0 | 42
  [40]   45: aload_1 | 43
  [40]   46: invokestatic test.output.HelloWorldReflect.invokeHellos(String[], ClassLoader):void | 184 0 13
  [41]   49: aload_0 | 42
  [41]   50: aload_2 | 44
  [41]   51: invokestatic test.output.HelloWorldReflect.invokeHellos(String[], ClassLoader):void | 184 0 13
  [44]   54: goto 62 | 167 0 8
  [42]   57: astore_1 | 76
  [43]   58: aload_1 | 43
  [43]   59: invokevirtual java.lang.Throwable.printStackTrace():void | 182 0 15
  [45]   62: return | 177
  Exception Handlers:
    from  to  target  type
    0     54  57      java.lang.Exception
  StackMapTable: number of entries = 4
    34: frame_type = 255 /* full_frame */
      offset_delta = 34
      number_of_locals = 3
      locals = [ java.lang.String[], java.lang.ClassLoader, java.lang.ClassLoader ]
      number_of_stack_items = 2
      stack = [ java.io.PrintStream, java.lang.StringBuilder ]
    35: frame_type = 255 /* full_frame */
      offset_delta = 0
      number_of_locals = 3
      locals = [ java.lang.String[], java.lang.ClassLoader, java.lang.ClassLoader ]
      number_of_stack_items = 3
      stack = [ java.io.PrintStream, java.lang.StringBuilder, int ]
    57: frame_type = 255 /* full_frame */
      offset_delta = 21
      number_of_locals = 1
      locals = [ java.lang.String[] ]
      number_of_stack_items = 1
      stack = [ java.lang.Exception ]
    62: frame_type = 4 /* same_frame */
      offset_delta = 4 /* implicit */
  LineNumberTable:
    line 35: 0
    line 36: 6
    line 38: 10
    line 40: 44
    line 41: 49
    line 44: 54
    line 42: 57
    line 43: 58
    line 45: 62
  LocalVariableTable:
    Start Length Slot Name               Descriptor            Generic-signature
    10    44     2    systemClassLoader  Ljava/lang/ClassLoader;
    6     48     1    thisClassLoader    Ljava/lang/ClassLoader;
    58    4      1    e                  Ljava/lang/Exception; 
    0     63     0    args               [Ljava/lang/String;   
   <|@
end_bytecodes
begin_compilation
  name " test.output.HelloWorldLoop::main"
  method "static void test.output.HelloWorldLoop.main(String[])"
  date 1588016546057
end_compilation
begin_cfg
  name "T1X static void test.output.HelloWorldLoop.main(java.lang.String[])"
end_cfg
begin_nmethod
  0x4002B7E8   000          jmp       L1: +8                                   [E9 08 00 00 00]
  0x4002B7ED   005          nop                                                [90]
  0x4002B7EE   006          nop                                                [90]
  0x4002B7EF   007          nop                                                [90]
  0x4002B7F0   008          call      L1: +0 OPT2BASELINE-Adapter(R)           [E8 00 00 00 00]
  ;; reg-ref-map: {}
  ;; frame-ref-map: {}
  ;; at test.output.HelloWorldLoop.main(String[]) [bci: -1]
  ;;             |0           |1          
  ;;    locals:  |[rbp+80]:j  |[rbp-16]:j 
  ;;    stack:   |[rbp-32]:j  |[rbp-48]:j
  0x4002B7F5   013   L1 :   enter     0x50, 0x0                                [C8 50 00 00]
  0x4002B7F9   017          subq      rbp, 0x40                                [48 83 ED 40]
  0x4002B7FD   021          mov       [rsp - 8104], rax                        [48 89 84 24 58 E0 FF FF]
  0x4002B805   029          xor       r11, r11                                 [4D 33 DB]
  0x4002B808   032          mov       [-151], r11                              [4C 89 1D 69 FF FF FF]
  0x4002B80F   039          mov       rdi, [-150]                              [48 8B 3D 6A FF FF FF]
  ;; reg-ref-map: rdi {7}
  ;; frame-ref-map: rbp+80 {16}
  ;; at test.output.HelloWorldLoop.main(String[]) [bci: -1]
  ;;             |0           |1          
  ;;    locals:  |[rbp+80]:a  |[rbp-16]:j 
  ;;    stack:   |[rbp-32]:j  |[rbp-48]:j
  0x4002B816   046          movsxd    rsi, [rdi + 48]                          [48 63 77 30]
  0x4002B81A   050          subl      esi, 0x1                                 [83 EE 01]
  0x4002B81D   053          .byte 0x40                                         [40]
  0x4002B81E   054          mov       [rdi + 48], esi                          [89 77 30]
  0x4002B821   057          cmpl      esi, 0x0                                 [83 FE 00]
  0x4002B824   060          jnle      L3: +17                                  [0F 8F 11 00 00 00]
  0x4002B82A   066          mov       rsi, 0x0                                 [48 BE 00 00 00 00 00 00 00 00]
  0x4002B834   076          nop                                                [90]
  0x4002B835   077          call      L2: +0 com.sun.max.vm.compiler.CompilationBroker.instrumentationCounterOverflow(MethodProfile, Object)   [E8 00 00 00 00]
  ;; reg-ref-map: {}
  ;; frame-ref-map: rbp+80 {16}
  ;; at test.output.HelloWorldLoop.main(String[]) [bci: -1]
  ;;             |0           |1          
  ;;    locals:  |[rbp+80]:a  |[rbp-16]:j 
  ;;    stack:   |[rbp-32]:j  |[rbp-48]:j
  0x4002B83A   082   L2 :   nop                                                [90]
  ;; -------------------- 0: getstatic 0 2 --------------------------------------------------------------
  0x4002B83B   083   L3 :   mov       rdi, [-186]                              [48 8B 3D 46 FF FF FF]
  0x4002B842   090          mov       esi, 0x18                                [BE 18 00 00 00]
  0x4002B847   095          movsxd    rsi, esi                                 [48 63 F6]
  ;; reg-ref-map: {}
  ;; frame-ref-map: rbp+80 {16}
  ;; at test.output.HelloWorldLoop.main(HelloWorldLoop.java:30) [bci: 0]
  ;;             |0           |1          
  ;;    locals:  |[rbp+80]:a  |[rbp-16]:j 
  ;;    stack:   |[rbp-32]:j  |[rbp-48]:j
  0x4002B84A   098          mov       rax, rdi[rsi]                            [48 8B 04 37]
  0x4002B84E   102          subq      rsp, 0x10                                [48 83 EC 10]
  0x4002B852   106          mov       [rsp], rax                               [48 89 04 24]
  ;; -------------------- 3: ldc 3 ----------------------------------------------------------------------
  0x4002B856   110          mov       r11, [-205]                              [4C 8B 1D 33 FF FF FF]
  0x4002B85D   117          subq      rsp, 0x10                                [48 83 EC 10]
  0x4002B861   121          mov       [rsp], r11                               [4C 89 1C 24]
  ;; -------------------- 5: invokevirtual 0 4 ----------------------------------------------------------
  0x4002B865   125          mov       edi, 0x2F                                [BF 2F 00 00 00]
  0x4002B86A   130          mov       rsi, [rsp + 16]                          [48 8B 74 24 10]
  0x4002B86F   135          mov       rdx, [-222]                              [48 8B 15 22 FF FF FF]
  0x4002B876   142          mov       ecx, 0x1                                 [B9 01 00 00 00]
  0x4002B87B   147          mov       rax, rsi                                 [48 8B C6]
  ;; reg-ref-map: rdx rsi {2, 6}
  ;; frame-ref-map: rbp-48 rbp-32 rbp+80 {0, 2, 16}
  ;; at test.output.HelloWorldLoop.main(HelloWorldLoop.java:30) [bci: 5]
  ;;             |0           |1          
  ;;    locals:  |[rbp+80]:a  |[rbp-16]:j 
  ;;    stack:   |[rbp-32]:a  |[rbp-48]:a
  0x4002B87E   150          mov       rax, [rax]                               [48 8B 00]
  0x4002B881   153          movsxd    rdi, edi                                 [48 63 FF]
  ;; reg-ref-map: rdx rsi {2, 6}
  ;; frame-ref-map: rbp-48 rbp-32 rbp+80 {0, 2, 16}
  ;; at test.output.HelloWorldLoop.main(HelloWorldLoop.java:30) [bci: 5]
  ;;             |0           |1          
  ;;    locals:  |[rbp+80]:a  |[rbp-16]:j 
  ;;    stack:   |[rbp-32]:a  |[rbp-48]:a
  0x4002B884   156          mov       rax, rax[rdi * 8 + 24]                   [48 8B 44 F8 18]
  0x4002B889   161          mov       rdi, rdx                                 [48 8B FA]
  0x4002B88C   164          mov       rdx, rcx                                 [48 8B D1]
  0x4002B88F   167          mov       ecx, 0x3                                 [B9 03 00 00 00]
  0x4002B894   172          mov       [rbp + 8], rax                           [48 89 45 08]
  0x4002B898   176          nop                                                [90]
  0x4002B899   177          nop                                                [90]
  0x4002B89A   178          call      L4: +0 com.sun.max.vm.profile.MethodInstrumentation.recordType(MethodProfile, Object, int, int)   [E8 00 00 00 00]
  ;; reg-ref-map: {}
  ;; frame-ref-map: rbp-48 rbp-32 rbp+80 {0, 2, 16}
  ;; at test.output.HelloWorldLoop.main(HelloWorldLoop.java:30) [bci: 5]
  ;;             |0           |1          
  ;;    locals:  |[rbp+80]:a  |[rbp-16]:j 
  ;;    stack:   |[rbp-32]:a  |[rbp-48]:a
  0x4002B89F   183   L4 :   nop                                                [90]
  0x4002B8A0   184          mov       rax, [rbp + 8]                           [48 8B 45 08]
  0x4002B8A4   188          addq      rax, 0xF8                                [48 83 C0 F8]
  0x4002B8A8   192          mov       rdi, [rsp + 16]                          [48 8B 7C 24 10]
  0x4002B8AD   197          call      rax <template_call>                      [FF D0]
  ;; reg-ref-map: {}
  ;; frame-ref-map: rbp+80 {16}
  ;; at test.output.HelloWorldLoop.main(HelloWorldLoop.java:30) [bci: 5]
  ;;             |0           |1          
  ;;    locals:  |[rbp+80]:a  |[rbp-16]:j 
  ;;    stack:   |[rbp-32]:j  |[rbp-48]:j
  0x4002B8AF   199          nop                                                [90]
  ;; -------------------- 8: iconst_0 -------------------------------------------------------------------
  0x4002B8B0   200          mov       r11d, 0x0                                [41 BB 00 00 00 00]
  0x4002B8B6   206          subq      rsp, 0x10                                [48 83 EC 10]
  0x4002B8BA   210          mov       [rsp], r11d                              [44 89 1C 24]
  ;; -------------------- 9: istore_1 -------------------------------------------------------------------
  0x4002B8BE   214          mov       r11d, [rsp]                              [44 8B 1C 24]
  0x4002B8C2   218          addq      rsp, 0x10                                [48 83 C4 10]
  0x4002B8C6   222          mov       [rbp - 16], r11d                         [44 89 5D F0]
  ;; -------------------- 10: iload_1 -------------------------------------------------------------------
  0x4002B8CA   226   L5 :   mov       r11d, [rbp - 16]                         [44 8B 5D F0]
  0x4002B8CE   230          subq      rsp, 0x10                                [48 83 EC 10]
  0x4002B8D2   234          mov       [rsp], r11d                              [44 89 1C 24]
  ;; -------------------- 11: ldc 5 ---------------------------------------------------------------------
  0x4002B8D6   238          mov       r11d, 0xF4240                            [41 BB 40 42 0F 00]
  0x4002B8DC   244          subq      rsp, 0x10                                [48 83 EC 10]
  0x4002B8E0   248          mov       [rsp], r11d                              [44 89 1C 24]
  ;; -------------------- 13: if_icmpge 0 11 ------------------------------------------------------------
  0x4002B8E4   252          mov       r11d, [rsp + 16]                         [44 8B 5C 24 10]
  0x4002B8E9   257          mov       eax, [rsp]                               [8B 04 24]
  0x4002B8EC   260          addq      rsp, 0x20                                [48 83 C4 20]
  0x4002B8F0   264          cmp       r11d, eax                                [44 3B D8]
  0x4002B8F3   267          jl        L7: +51                                  [7C 33]
  0x4002B8F5   269          mov       rdi, [-348]                              [48 8B 3D A4 FE FF FF]
  0x4002B8FC   276          mov       esi, 0x9                                 [BE 09 00 00 00]
  ;; reg-ref-map: rdi {7}
  ;; frame-ref-map: rbp+80 {16}
  ;; at test.output.HelloWorldLoop.main(HelloWorldLoop.java:33) [bci: 13]
  ;;             |0           |1          
  ;;    locals:  |[rbp+80]:a  |[rbp-16]:j 
  ;;    stack:   |[rbp-32]:j  |[rbp-48]:j
  0x4002B901   281          mov       rax, [rdi + 24]                          [48 8B 47 18]
  0x4002B905   285          mov       rcx, rax                                 [48 8B C8]
  0x4002B908   288          movsxd    rsi, esi                                 [48 63 F6]
  ;; reg-ref-map: rax {0}
  ;; frame-ref-map: rbp+80 {16}
  ;; at test.output.HelloWorldLoop.main(HelloWorldLoop.java:33) [bci: 13]
  ;;             |0           |1          
  ;;    locals:  |[rbp+80]:a  |[rbp-16]:j 
  ;;    stack:   |[rbp-32]:j  |[rbp-48]:j
  0x4002B90B   291          movsxd    rcx, rcx[rsi * 4 + 24]                   [48 63 4C B1 18]
  0x4002B910   296          cmpl      ecx, 0x7FFFFFFF                          [81 F9 FF FF FF 7F]
  0x4002B916   302          jnl       L6: +7                                   [0F 8D 07 00 00 00]
  0x4002B91C   308          addl      ecx, 0x1                                 [83 C1 01]
  0x4002B91F   311          mov       rax[rsi * 4 + 24], ecx                   [89 4C B0 18]
  0x4002B923   315   L6 :   jmp       L11: +155                                [E9 9B 00 00 00]
  0x4002B928   320   L7 :   mov       rdi, [-391]                              [48 8B 3D 79 FE FF FF]
  0x4002B92F   327          mov       esi, 0xA                                 [BE 0A 00 00 00]
  ;; reg-ref-map: rdi {7}
  ;; frame-ref-map: rbp+80 {16}
  ;; at test.output.HelloWorldLoop.main(HelloWorldLoop.java:33) [bci: 13]
  ;;             |0           |1          
  ;;    locals:  |[rbp+80]:a  |[rbp-16]:j 
  ;;    stack:   |[rbp-32]:j  |[rbp-48]:j
  0x4002B934   332          mov       rax, [rdi + 24]                          [48 8B 47 18]
  0x4002B938   336          mov       rcx, rax                                 [48 8B C8]
  0x4002B93B   339          movsxd    rsi, esi                                 [48 63 F6]
  ;; reg-ref-map: rax {0}
  ;; frame-ref-map: rbp+80 {16}
  ;; at test.output.HelloWorldLoop.main(HelloWorldLoop.java:33) [bci: 13]
  ;;             |0           |1          
  ;;    locals:  |[rbp+80]:a  |[rbp-16]:j 
  ;;    stack:   |[rbp-32]:j  |[rbp-48]:j
  0x4002B93E   342          movsxd    rcx, rcx[rsi * 4 + 24]                   [48 63 4C B1 18]
  0x4002B943   347          cmpl      ecx, 0x7FFFFFFF                          [81 F9 FF FF FF 7F]
  0x4002B949   353          jnl       L8: +7                                   [0F 8D 07 00 00 00]
  0x4002B94F   359          addl      ecx, 0x1                                 [83 C1 01]
  0x4002B952   362          mov       rax[rsi * 4 + 24], ecx                   [89 4C B0 18]
  ;; -------------------- 16: iload_1 -------------------------------------------------------------------
  0x4002B956   366   L8 :   mov       r11d, [rbp - 16]                         [44 8B 5D F0]
  0x4002B95A   370          subq      rsp, 0x10                                [48 83 EC 10]
  0x4002B95E   374          mov       [rsp], r11d                              [44 89 1C 24]
  ;; -------------------- 17: invokestatic 0 6 ----------------------------------------------------------
  0x4002B962   378          call      L9: +0 test.output.HelloWorldLoop.increment(int)   [E8 00 00 00 00]
  ;; reg-ref-map: {}
  ;; frame-ref-map: rbp+80 {16}
  ;; at test.output.HelloWorldLoop.main(HelloWorldLoop.java:34) [bci: 17]
  ;;             |0           |1          
  ;;    locals:  |[rbp+80]:a  |[rbp-16]:j 
  ;;    stack:   |[rbp-32]:j  |[rbp-48]:j
  0x4002B967   383   L9 :   nop                                                [90]
  0x4002B968   384          subq      rsp, 0x10                                [48 83 EC 10]
  0x4002B96C   388          mov       [rsp], rax                               [48 89 04 24]
  ;; -------------------- 20: istore_1 ------------------------------------------------------------------
  0x4002B970   392          mov       r11d, [rsp]                              [44 8B 1C 24]
  0x4002B974   396          addq      rsp, 0x10                                [48 83 C4 10]
  0x4002B978   400          mov       [rbp - 16], r11d                         [44 89 5D F0]
  ;; -------------------- 21: goto 255 245 --------------------------------------------------------------
  0x4002B97C   404          mov       rdi, [-467]                              [48 8B 3D 2D FE FF FF]
  0x4002B983   411          mov       esi, 0xC                                 [BE 0C 00 00 00]
  ;; reg-ref-map: rdi {7}
  ;; frame-ref-map: rbp+80 {16}
  ;; at test.output.HelloWorldLoop.main(HelloWorldLoop.java:34) [bci: 21]
  ;;             |0           |1          
  ;;    locals:  |[rbp+80]:a  |[rbp-16]:j 
  ;;    stack:   |[rbp-32]:j  |[rbp-48]:j
  0x4002B988   416          mov       rax, [rdi + 24]                          [48 8B 47 18]
  0x4002B98C   420          mov       rcx, rax                                 [48 8B C8]
  0x4002B98F   423          movsxd    rsi, esi                                 [48 63 F6]
  ;; reg-ref-map: rax {0}
  ;; frame-ref-map: rbp+80 {16}
  ;; at test.output.HelloWorldLoop.main(HelloWorldLoop.java:34) [bci: 21]
  ;;             |0           |1          
  ;;    locals:  |[rbp+80]:a  |[rbp-16]:j 
  ;;    stack:   |[rbp-32]:j  |[rbp-48]:j
  0x4002B992   426          movsxd    rcx, rcx[rsi * 4 + 24]                   [48 63 4C B1 18]
  0x4002B997   431          cmpl      ecx, 0x7FFFFFFF                          [81 F9 FF FF FF 7F]
  0x4002B99D   437          jnl       L10: +7                                  [0F 8D 07 00 00 00]
  0x4002B9A3   443          addl      ecx, 0x1                                 [83 C1 01]
  0x4002B9A6   446          mov       rax[rsi * 4 + 24], ecx                   [89 4C B0 18]
  0x4002B9AA   450   L10:   mov       rdi, [-505]                              [48 8B 3D 07 FE FF FF]
  ;; reg-ref-map: rdi {7}
  ;; frame-ref-map: rbp+80 {16}
  ;; at test.output.HelloWorldLoop.main(HelloWorldLoop.java:34) [bci: 21]
  ;;             |0           |1          
  ;;    locals:  |[rbp+80]:a  |[rbp-16]:j 
  ;;    stack:   |[rbp-32]:j  |[rbp-48]:j
  0x4002B9B1   457          movsxd    rax, [rdi + 48]                          [48 63 47 30]
  0x4002B9B5   461          subl      eax, 0x1                                 [83 E8 01]
  0x4002B9B8   464          mov       [rdi + 48], eax                          [89 47 30]
  ;; reg-ref-map: {}
  ;; frame-ref-map: rbp+80 {16}
  ;; at test.output.HelloWorldLoop.main(HelloWorldLoop.java:34) [bci: 21]
  ;;             |0           |1          
  ;;    locals:  |[rbp+80]:a  |[rbp-16]:j 
  ;;    stack:   |[rbp-32]:j  |[rbp-48]:j
  0x4002B9BB   467          mov       r14, [r14]                               [4D 8B 36]
  0x4002B9BE   470          jmp       L5: -249                                 [E9 07 FF FF FF]
  ;; -------------------- 24: getstatic 0 2 -------------------------------------------------------------
  0x4002B9C3   475   L11:   mov       rdi, [-522]                              [48 8B 3D F6 FD FF FF]
  0x4002B9CA   482          mov       esi, 0x18                                [BE 18 00 00 00]
  0x4002B9CF   487          movsxd    rsi, esi                                 [48 63 F6]
  ;; reg-ref-map: {}
  ;; frame-ref-map: rbp+80 {16}
  ;; at test.output.HelloWorldLoop.main(HelloWorldLoop.java:37) [bci: 24]
  ;;             |0           |1          
  ;;    locals:  |[rbp+80]:a  |[rbp-16]:j 
  ;;    stack:   |[rbp-32]:j  |[rbp-48]:j
  0x4002B9D2   490          mov       rax, rdi[rsi]                            [48 8B 04 37]
  0x4002B9D6   494          subq      rsp, 0x10                                [48 83 EC 10]
  0x4002B9DA   498          mov       [rsp], rax                               [48 89 04 24]
  ;; -------------------- 27: iload_1 -------------------------------------------------------------------
  0x4002B9DE   502          mov       r11d, [rbp - 16]                         [44 8B 5D F0]
  0x4002B9E2   506          subq      rsp, 0x10                                [48 83 EC 10]
  0x4002B9E6   510          mov       [rsp], r11d                              [44 89 1C 24]
  ;; -------------------- 28: invokevirtual 0 7 ---------------------------------------------------------
  0x4002B9EA   514          mov       edi, 0x2A                                [BF 2A 00 00 00]
  0x4002B9EF   519          mov       rsi, [rsp + 16]                          [48 8B 74 24 10]
  0x4002B9F4   524          mov       rdx, [-563]                              [48 8B 15 CD FD FF FF]
  0x4002B9FB   531          mov       ecx, 0xE                                 [B9 0E 00 00 00]
  0x4002BA00   536          mov       rax, rsi                                 [48 8B C6]
  ;; reg-ref-map: rdx rsi {2, 6}
  ;; frame-ref-map: rbp-32 rbp+80 {2, 16}
  ;; at test.output.HelloWorldLoop.main(HelloWorldLoop.java:37) [bci: 28]
  ;;             |0           |1          
  ;;    locals:  |[rbp+80]:a  |[rbp-16]:j 
  ;;    stack:   |[rbp-32]:a  |[rbp-48]:j
  0x4002BA03   539          mov       rax, [rax]                               [48 8B 00]
  0x4002BA06   542          movsxd    rdi, edi                                 [48 63 FF]
  ;; reg-ref-map: rdx rsi {2, 6}
  ;; frame-ref-map: rbp-32 rbp+80 {2, 16}
  ;; at test.output.HelloWorldLoop.main(HelloWorldLoop.java:37) [bci: 28]
  ;;             |0           |1          
  ;;    locals:  |[rbp+80]:a  |[rbp-16]:j 
  ;;    stack:   |[rbp-32]:a  |[rbp-48]:j
  0x4002BA09   545          mov       rax, rax[rdi * 8 + 24]                   [48 8B 44 F8 18]
  0x4002BA0E   550          mov       rdi, rdx                                 [48 8B FA]
  0x4002BA11   553          mov       rdx, rcx                                 [48 8B D1]
  0x4002BA14   556          mov       ecx, 0x3                                 [B9 03 00 00 00]
  0x4002BA19   561          mov       [rbp + 8], rax                           [48 89 45 08]
  0x4002BA1D   565          nop                                                [90]
  0x4002BA1E   566          nop                                                [90]
  0x4002BA1F   567          call      L12: +0 com.sun.max.vm.profile.MethodInstrumentation.recordType(MethodProfile, Object, int, int)   [E8 00 00 00 00]
  ;; reg-ref-map: {}
  ;; frame-ref-map: rbp-32 rbp+80 {2, 16}
  ;; at test.output.HelloWorldLoop.main(HelloWorldLoop.java:37) [bci: 28]
  ;;             |0           |1          
  ;;    locals:  |[rbp+80]:a  |[rbp-16]:j 
  ;;    stack:   |[rbp-32]:a  |[rbp-48]:j
  0x4002BA24   572   L12:   nop                                                [90]
  0x4002BA25   573          mov       rax, [rbp + 8]                           [48 8B 45 08]
  0x4002BA29   577          addq      rax, 0xF8                                [48 83 C0 F8]
  0x4002BA2D   581          mov       rdi, [rsp + 16]                          [48 8B 7C 24 10]
  0x4002BA32   586          call      rax <template_call>                      [FF D0]
  ;; reg-ref-map: {}
  ;; frame-ref-map: rbp+80 {16}
  ;; at test.output.HelloWorldLoop.main(HelloWorldLoop.java:37) [bci: 28]
  ;;             |0           |1          
  ;;    locals:  |[rbp+80]:a  |[rbp-16]:j 
  ;;    stack:   |[rbp-32]:j  |[rbp-48]:j
  0x4002BA34   588          nop                                                [90]
  ;; -------------------- 31: return --------------------------------------------------------------------
  0x4002BA35   589          addq      rbp, 0x40                                [48 83 C5 40]
  0x4002BA39   593          leave                                              [C9]
  0x4002BA3A   594          ret       0x10                                     [C2 10 00]
   <|@
end_nmethod
begin_bytecodes
  public static void test.output.HelloWorldLoop.main(java.lang.String[])
  Stack=2, Locals=2
  [30]   0: getstatic java.lang.System.out:PrintStream | 178 0 2
  [30]   3: ldc "Hello World!" | 18 3
  [30]   5: invokevirtual java.io.PrintStream.println(String):void | 182 0 4
  [32]   8: iconst_0 | 3
  [32]   9: istore_1 | 60
  [33]   10: iload_1 | 27
  [33]   11: ldc 1000000 | 18 5
  [33]   13: if_icmpge 24 | 162 0 11
  [34]   16: iload_1 | 27
  [34]   17: invokestatic test.output.HelloWorldLoop.increment(int):int | 184 0 6
  [34]   20: istore_1 | 60
  [34]   21: goto 10 | 167 255 245
  [37]   24: getstatic java.lang.System.out:PrintStream | 178 0 2
  [37]   27: iload_1 | 27
  [37]   28: invokevirtual java.io.PrintStream.println(int):void | 182 0 7
  [38]   31: return | 177
  StackMapTable: number of entries = 2
    10: frame_type = 252 /* append_frame */
      offset_delta = 10
      locals = [ int ]
    24: frame_type = 13 /* same_frame */
      offset_delta = 13 /* implicit */
  LineNumberTable:
    line 30: 0
    line 32: 8
    line 33: 10
    line 34: 16
    line 37: 24
    line 38: 31
  LocalVariableTable:
    Start Length Slot Name               Descriptor            Generic-signature
    0     32     0    args               [Ljava/lang/String;   
    10    22     1    i                  I                     
   <|@
end_bytecodes
begin_compilation
  name " test.output.HelloWorldGC::main"
  method "static void test.output.HelloWorldGC.main(String[])"
  date 1588016546096
end_compilation
begin_cfg
  name "T1X static void test.output.HelloWorldGC.main(java.lang.String[])"
end_cfg
begin_nmethod
  0x4002BAB0   000         jmp       L1: +8                                   [E9 08 00 00 00]
  0x4002BAB5   005         nop                                                [90]
  0x4002BAB6   006         nop                                                [90]
  0x4002BAB7   007         nop                                                [90]
  0x4002BAB8   008         call      L1: +0 OPT2BASELINE-Adapter(R)           [E8 00 00 00 00]
  ;; reg-ref-map: {}
  ;; frame-ref-map: {}
  ;; at test.output.HelloWorldGC.main(String[]) [bci: -1]
  ;;             |0           |1          
  ;;    locals:  |[rbp+80]:j  |           
  ;;    stack:   |[rbp-16]:j  |[rbp-32]:j
  0x4002BABD   013   L1:   enter     0x40, 0x0                                [C8 40 00 00]
  0x4002BAC1   017         subq      rbp, 0x40                                [48 83 ED 40]
  0x4002BAC5   021         mov       [rsp - 8120], rax                        [48 89 84 24 48 E0 FF FF]
  0x4002BACD   029         xor       r11, r11                                 [4D 33 DB]
  0x4002BAD0   032         mov       [-127], r11                              [4C 89 1D 81 FF FF FF]
  0x4002BAD7   039         mov       rdi, [-126]                              [48 8B 3D 82 FF FF FF]
  ;; reg-ref-map: rdi {7}
  ;; frame-ref-map: rbp+80 {14}
  ;; at test.output.HelloWorldGC.main(String[]) [bci: -1]
  ;;             |0           |1          
  ;;    locals:  |[rbp+80]:a  |           
  ;;    stack:   |[rbp-16]:j  |[rbp-32]:j
  0x4002BADE   046         movsxd    rsi, [rdi + 48]                          [48 63 77 30]
  0x4002BAE2   050         subl      esi, 0x1                                 [83 EE 01]
  0x4002BAE5   053         .byte 0x40                                         [40]
  0x4002BAE6   054         mov       [rdi + 48], esi                          [89 77 30]
  0x4002BAE9   057         cmpl      esi, 0x0                                 [83 FE 00]
  0x4002BAEC   060         jnle      L3: +17                                  [0F 8F 11 00 00 00]
  0x4002BAF2   066         mov       rsi, 0x0                                 [48 BE 00 00 00 00 00 00 00 00]
  0x4002BAFC   076         nop                                                [90]
  0x4002BAFD   077         call      L2: +0 com.sun.max.vm.compiler.CompilationBroker.instrumentationCounterOverflow(MethodProfile, Object)   [E8 00 00 00 00]
  ;; reg-ref-map: {}
  ;; frame-ref-map: rbp+80 {14}
  ;; at test.output.HelloWorldGC.main(String[]) [bci: -1]
  ;;             |0           |1          
  ;;    locals:  |[rbp+80]:a  |           
  ;;    stack:   |[rbp-16]:j  |[rbp-32]:j
  0x4002BB02   082   L2:   nop                                                [90]
  ;; -------------------- 0: getstatic 0 2 --------------------------------------------------------------
  0x4002BB03   083   L3:   mov       rdi, [-162]                              [48 8B 3D 5E FF FF FF]
  0x4002BB0A   090         mov       esi, 0x18                                [BE 18 00 00 00]
  0x4002BB0F   095         movsxd    rsi, esi                                 [48 63 F6]
  ;; reg-ref-map: {}
  ;; frame-ref-map: rbp+80 {14}
  ;; at test.output.HelloWorldGC.main(HelloWorldGC.java:32) [bci: 0]
  ;;             |0           |1          
  ;;    locals:  |[rbp+80]:a  |           
  ;;    stack:   |[rbp-16]:j  |[rbp-32]:j
  0x4002BB12   098         mov       rax, rdi[rsi]                            [48 8B 04 37]
  0x4002BB16   102         subq      rsp, 0x10                                [48 83 EC 10]
  0x4002BB1A   106         mov       [rsp], rax                               [48 89 04 24]
  ;; -------------------- 3: ldc 3 ----------------------------------------------------------------------
  0x4002BB1E   110         mov       r11, [-181]                              [4C 8B 1D 4B FF FF FF]
  0x4002BB25   117         subq      rsp, 0x10                                [48 83 EC 10]
  0x4002BB29   121         mov       [rsp], r11                               [4C 89 1C 24]
  ;; -------------------- 5: invokevirtual 0 4 ----------------------------------------------------------
  0x4002BB2D   125         mov       edi, 0x2F                                [BF 2F 00 00 00]
  0x4002BB32   130         mov       rsi, [rsp + 16]                          [48 8B 74 24 10]
  0x4002BB37   135         mov       rdx, [-198]                              [48 8B 15 3A FF FF FF]
  0x4002BB3E   142         mov       ecx, 0x1                                 [B9 01 00 00 00]
  0x4002BB43   147         mov       rax, rsi                                 [48 8B C6]
  ;; reg-ref-map: rdx rsi {2, 6}
  ;; frame-ref-map: rbp-32 rbp-16 rbp+80 {0, 2, 14}
  ;; at test.output.HelloWorldGC.main(HelloWorldGC.java:32) [bci: 5]
  ;;             |0           |1          
  ;;    locals:  |[rbp+80]:a  |           
  ;;    stack:   |[rbp-16]:a  |[rbp-32]:a
  0x4002BB46   150         mov       rax, [rax]                               [48 8B 00]
  0x4002BB49   153         movsxd    rdi, edi                                 [48 63 FF]
  ;; reg-ref-map: rdx rsi {2, 6}
  ;; frame-ref-map: rbp-32 rbp-16 rbp+80 {0, 2, 14}
  ;; at test.output.HelloWorldGC.main(HelloWorldGC.java:32) [bci: 5]
  ;;             |0           |1          
  ;;    locals:  |[rbp+80]:a  |           
  ;;    stack:   |[rbp-16]:a  |[rbp-32]:a
  0x4002BB4C   156         mov       rax, rax[rdi * 8 + 24]                   [48 8B 44 F8 18]
  0x4002BB51   161         mov       rdi, rdx                                 [48 8B FA]
  0x4002BB54   164         mov       rdx, rcx                                 [48 8B D1]
  0x4002BB57   167         mov       ecx, 0x3                                 [B9 03 00 00 00]
  0x4002BB5C   172         mov       [rbp + 8], rax                           [48 89 45 08]
  0x4002BB60   176         nop                                                [90]
  0x4002BB61   177         nop                                                [90]
  0x4002BB62   178         call      L4: +0 com.sun.max.vm.profile.MethodInstrumentation.recordType(MethodProfile, Object, int, int)   [E8 00 00 00 00]
  ;; reg-ref-map: {}
  ;; frame-ref-map: rbp-32 rbp-16 rbp+80 {0, 2, 14}
  ;; at test.output.HelloWorldGC.main(HelloWorldGC.java:32) [bci: 5]
  ;;             |0           |1          
  ;;    locals:  |[rbp+80]:a  |           
  ;;    stack:   |[rbp-16]:a  |[rbp-32]:a
  0x4002BB67   183   L4:   nop                                                [90]
  0x4002BB68   184         mov       rax, [rbp + 8]                           [48 8B 45 08]
  0x4002BB6C   188         addq      rax, 0xF8                                [48 83 C0 F8]
  0x4002BB70   192         mov       rdi, [rsp + 16]                          [48 8B 7C 24 10]
  0x4002BB75   197         call      rax <template_call>                      [FF D0]
  ;; reg-ref-map: {}
  ;; frame-ref-map: rbp+80 {14}
  ;; at test.output.HelloWorldGC.main(HelloWorldGC.java:32) [bci: 5]
  ;;             |0           |1          
  ;;    locals:  |[rbp+80]:a  |           
  ;;    stack:   |[rbp-16]:j  |[rbp-32]:j
  0x4002BB77   199         nop                                                [90]
  ;; -------------------- 8: invokestatic 0 5 -----------------------------------------------------------
  0x4002BB78   200         call      L5: +0 java.lang.System.gc()             [E8 00 00 00 00]
  ;; reg-ref-map: {}
  ;; frame-ref-map: rbp+80 {14}
  ;; at test.output.HelloWorldGC.main(HelloWorldGC.java:33) [bci: 8]
  ;;             |0           |1          
  ;;    locals:  |[rbp+80]:a  |           
  ;;    stack:   |[rbp-16]:j  |[rbp-32]:j
  0x4002BB7D   205   L5:   nop                                                [90]
  ;; -------------------- 11: getstatic 0 2 -------------------------------------------------------------
  0x4002BB7E   206         mov       rdi, [-261]                              [48 8B 3D FB FE FF FF]
  0x4002BB85   213         mov       esi, 0x18                                [BE 18 00 00 00]
  0x4002BB8A   218         movsxd    rsi, esi                                 [48 63 F6]
  ;; reg-ref-map: {}
  ;; frame-ref-map: rbp+80 {14}
  ;; at test.output.HelloWorldGC.main(HelloWorldGC.java:34) [bci: 11]
  ;;             |0           |1          
  ;;    locals:  |[rbp+80]:a  |           
  ;;    stack:   |[rbp-16]:j  |[rbp-32]:j
  0x4002BB8D   221         mov       rax, rdi[rsi]                            [48 8B 04 37]
  0x4002BB91   225         subq      rsp, 0x10                                [48 83 EC 10]
  0x4002BB95   229         mov       [rsp], rax                               [48 89 04 24]
  ;; -------------------- 14: ldc 3 ---------------------------------------------------------------------
  0x4002BB99   233         mov       r11, [-280]                              [4C 8B 1D E8 FE FF FF]
  0x4002BBA0   240         subq      rsp, 0x10                                [48 83 EC 10]
  0x4002BBA4   244         mov       [rsp], r11                               [4C 89 1C 24]
  ;; -------------------- 16: invokevirtual 0 4 ---------------------------------------------------------
  0x4002BBA8   248         mov       edi, 0x2F                                [BF 2F 00 00 00]
  0x4002BBAD   253         mov       rsi, [rsp + 16]                          [48 8B 74 24 10]
  0x4002BBB2   258         mov       rdx, [-297]                              [48 8B 15 D7 FE FF FF]
  0x4002BBB9   265         mov       ecx, 0xB                                 [B9 0B 00 00 00]
  0x4002BBBE   270         mov       rax, rsi                                 [48 8B C6]
  ;; reg-ref-map: rdx rsi {2, 6}
  ;; frame-ref-map: rbp-32 rbp-16 rbp+80 {0, 2, 14}
  ;; at test.output.HelloWorldGC.main(HelloWorldGC.java:34) [bci: 16]
  ;;             |0           |1          
  ;;    locals:  |[rbp+80]:a  |           
  ;;    stack:   |[rbp-16]:a  |[rbp-32]:a
  0x4002BBC1   273         mov       rax, [rax]                               [48 8B 00]
  0x4002BBC4   276         movsxd    rdi, edi                                 [48 63 FF]
  ;; reg-ref-map: rdx rsi {2, 6}
  ;; frame-ref-map: rbp-32 rbp-16 rbp+80 {0, 2, 14}
  ;; at test.output.HelloWorldGC.main(HelloWorldGC.java:34) [bci: 16]
  ;;             |0           |1          
  ;;    locals:  |[rbp+80]:a  |           
  ;;    stack:   |[rbp-16]:a  |[rbp-32]:a
  0x4002BBC7   279         mov       rax, rax[rdi * 8 + 24]                   [48 8B 44 F8 18]
  0x4002BBCC   284         mov       rdi, rdx                                 [48 8B FA]
  0x4002BBCF   287         mov       rdx, rcx                                 [48 8B D1]
  0x4002BBD2   290         mov       ecx, 0x3                                 [B9 03 00 00 00]
  0x4002BBD7   295         mov       [rbp + 8], rax                           [48 89 45 08]
  0x4002BBDB   299         nop                                                [90]
  0x4002BBDC   300         nop                                                [90]
  0x4002BBDD   301         call      L6: +0 com.sun.max.vm.profile.MethodInstrumentation.recordType(MethodProfile, Object, int, int)   [E8 00 00 00 00]
  ;; reg-ref-map: {}
  ;; frame-ref-map: rbp-32 rbp-16 rbp+80 {0, 2, 14}
  ;; at test.output.HelloWorldGC.main(HelloWorldGC.java:34) [bci: 16]
  ;;             |0           |1          
  ;;    locals:  |[rbp+80]:a  |           
  ;;    stack:   |[rbp-16]:a  |[rbp-32]:a
  0x4002BBE2   306   L6:   nop                                                [90]
  0x4002BBE3   307         mov       rax, [rbp + 8]                           [48 8B 45 08]
  0x4002BBE7   311         addq      rax, 0xF8                                [48 83 C0 F8]
  0x4002BBEB   315         mov       rdi, [rsp + 16]                          [48 8B 7C 24 10]
  0x4002BBF0   320         call      rax <template_call>                      [FF D0]
  ;; reg-ref-map: {}
  ;; frame-ref-map: rbp+80 {14}
  ;; at test.output.HelloWorldGC.main(HelloWorldGC.java:34) [bci: 16]
  ;;             |0           |1          
  ;;    locals:  |[rbp+80]:a  |           
  ;;    stack:   |[rbp-16]:j  |[rbp-32]:j
  0x4002BBF2   322         nop                                                [90]
  ;; -------------------- 19: return --------------------------------------------------------------------
  0x4002BBF3   323         addq      rbp, 0x40                                [48 83 C5 40]
  0x4002BBF7   327         leave                                              [C9]
  0x4002BBF8   328         ret       0x10                                     [C2 10 00]
   <|@
end_nmethod
begin_bytecodes
  public static void test.output.HelloWorldGC.main(java.lang.String[])
  Stack=2, Locals=1
  [32]   0: getstatic java.lang.System.out:PrintStream | 178 0 2
  [32]   3: ldc "Hello World!" | 18 3
  [32]   5: invokevirtual java.io.PrintStream.println(String):void | 182 0 4
  [33]   8: invokestatic java.lang.System.gc():void | 184 0 5
  [34]   11: getstatic java.lang.System.out:PrintStream | 178 0 2
  [34]   14: ldc "Hello World!" | 18 3
  [34]   16: invokevirtual java.io.PrintStream.println(String):void | 182 0 4
  [35]   19: return | 177
  LineNumberTable:
    line 32: 0
    line 33: 8
    line 34: 11
    line 35: 19
  LocalVariableTable:
    Start Length Slot Name               Descriptor            Generic-signature
    0     20     0    args               [Ljava/lang/String;   
   <|@
end_bytecodes
begin_compilation
  name " test.output.HelloWorld::main"
  method "static void test.output.HelloWorld.main(String[])"
  date 1588016546120
end_compilation
begin_cfg
  name "T1X static void test.output.HelloWorld.main(java.lang.String[])"
end_cfg
begin_nmethod
  0x4002BC58   000         jmp       L1: +8                                   [E9 08 00 00 00]
  0x4002BC5D   005         nop                                                [90]
  0x4002BC5E   006         nop                                                [90]
  0x4002BC5F   007         nop                                                [90]
  0x4002BC60   008         call      L1: +0 OPT2BASELINE-Adapter(R)           [E8 00 00 00 00]
  ;; reg-ref-map: {}
  ;; frame-ref-map: {}
  ;; at test.output.HelloWorld.main(String[]) [bci: -1]
  ;;             |0           |1          
  ;;    locals:  |[rbp+80]:j  |           
  ;;    stack:   |[rbp-16]:j  |[rbp-32]:j
  0x4002BC65   013   L1:   enter     0x40, 0x0                                [C8 40 00 00]
  0x4002BC69   017         subq      rbp, 0x40                                [48 83 ED 40]
  0x4002BC6D   021         mov       [rsp - 8120], rax                        [48 89 84 24 48 E0 FF FF]
  0x4002BC75   029         xor       r11, r11                                 [4D 33 DB]
  0x4002BC78   032         mov       [-103], r11                              [4C 89 1D 99 FF FF FF]
  0x4002BC7F   039         mov       rdi, [-102]                              [48 8B 3D 9A FF FF FF]
  ;; reg-ref-map: rdi {7}
  ;; frame-ref-map: rbp+80 {14}
  ;; at test.output.HelloWorld.main(String[]) [bci: -1]
  ;;             |0           |1          
  ;;    locals:  |[rbp+80]:a  |           
  ;;    stack:   |[rbp-16]:j  |[rbp-32]:j
  0x4002BC86   046         movsxd    rsi, [rdi + 48]                          [48 63 77 30]
  0x4002BC8A   050         subl      esi, 0x1                                 [83 EE 01]
  0x4002BC8D   053         .byte 0x40                                         [40]
  0x4002BC8E   054         mov       [rdi + 48], esi                          [89 77 30]
  0x4002BC91   057         cmpl      esi, 0x0                                 [83 FE 00]
  0x4002BC94   060         jnle      L3: +17                                  [0F 8F 11 00 00 00]
  0x4002BC9A   066         mov       rsi, 0x0                                 [48 BE 00 00 00 00 00 00 00 00]
  0x4002BCA4   076         nop                                                [90]
  0x4002BCA5   077         call      L2: +0 com.sun.max.vm.compiler.CompilationBroker.instrumentationCounterOverflow(MethodProfile, Object)   [E8 00 00 00 00]
  ;; reg-ref-map: {}
  ;; frame-ref-map: rbp+80 {14}
  ;; at test.output.HelloWorld.main(String[]) [bci: -1]
  ;;             |0           |1          
  ;;    locals:  |[rbp+80]:a  |           
  ;;    stack:   |[rbp-16]:j  |[rbp-32]:j
  0x4002BCAA   082   L2:   nop                                                [90]
  ;; -------------------- 0: getstatic 0 2 --------------------------------------------------------------
  0x4002BCAB   083   L3:   mov       rdi, [-138]                              [48 8B 3D 76 FF FF FF]
  0x4002BCB2   090         mov       esi, 0x18                                [BE 18 00 00 00]
  0x4002BCB7   095         movsxd    rsi, esi                                 [48 63 F6]
  ;; reg-ref-map: {}
  ;; frame-ref-map: rbp+80 {14}
  ;; at test.output.HelloWorld.main(HelloWorld.java:29) [bci: 0]
  ;;             |0           |1          
  ;;    locals:  |[rbp+80]:a  |           
  ;;    stack:   |[rbp-16]:j  |[rbp-32]:j
  0x4002BCBA   098         mov       rax, rdi[rsi]                            [48 8B 04 37]
  0x4002BCBE   102         subq      rsp, 0x10                                [48 83 EC 10]
  0x4002BCC2   106         mov       [rsp], rax                               [48 89 04 24]
  ;; -------------------- 3: ldc 3 ----------------------------------------------------------------------
  0x4002BCC6   110         mov       r11, [-157]                              [4C 8B 1D 63 FF FF FF]
  0x4002BCCD   117         subq      rsp, 0x10                                [48 83 EC 10]
  0x4002BCD1   121         mov       [rsp], r11                               [4C 89 1C 24]
  ;; -------------------- 5: invokevirtual 0 4 ----------------------------------------------------------
  0x4002BCD5   125         mov       edi, 0x2F                                [BF 2F 00 00 00]
  0x4002BCDA   130         mov       rsi, [rsp + 16]                          [48 8B 74 24 10]
  0x4002BCDF   135         mov       rdx, [-174]                              [48 8B 15 52 FF FF FF]
  0x4002BCE6   142         mov       ecx, 0x1                                 [B9 01 00 00 00]
  0x4002BCEB   147         mov       rax, rsi                                 [48 8B C6]
  ;; reg-ref-map: rdx rsi {2, 6}
  ;; frame-ref-map: rbp-32 rbp-16 rbp+80 {0, 2, 14}
  ;; at test.output.HelloWorld.main(HelloWorld.java:29) [bci: 5]
  ;;             |0           |1          
  ;;    locals:  |[rbp+80]:a  |           
  ;;    stack:   |[rbp-16]:a  |[rbp-32]:a
  0x4002BCEE   150         mov       rax, [rax]                               [48 8B 00]
  0x4002BCF1   153         movsxd    rdi, edi                                 [48 63 FF]
  ;; reg-ref-map: rdx rsi {2, 6}
  ;; frame-ref-map: rbp-32 rbp-16 rbp+80 {0, 2, 14}
  ;; at test.output.HelloWorld.main(HelloWorld.java:29) [bci: 5]
  ;;             |0           |1          
  ;;    locals:  |[rbp+80]:a  |           
  ;;    stack:   |[rbp-16]:a  |[rbp-32]:a
  0x4002BCF4   156         mov       rax, rax[rdi * 8 + 24]                   [48 8B 44 F8 18]
  0x4002BCF9   161         mov       rdi, rdx                                 [48 8B FA]
  0x4002BCFC   164         mov       rdx, rcx                                 [48 8B D1]
  0x4002BCFF   167         mov       ecx, 0x3                                 [B9 03 00 00 00]
  0x4002BD04   172         mov       [rbp + 8], rax                           [48 89 45 08]
  0x4002BD08   176         nop                                                [90]
  0x4002BD09   177         nop                                                [90]
  0x4002BD0A   178         call      L4: +0 com.sun.max.vm.profile.MethodInstrumentation.recordType(MethodProfile, Object, int, int)   [E8 00 00 00 00]
  ;; reg-ref-map: {}
  ;; frame-ref-map: rbp-32 rbp-16 rbp+80 {0, 2, 14}
  ;; at test.output.HelloWorld.main(HelloWorld.java:29) [bci: 5]
  ;;             |0           |1          
  ;;    locals:  |[rbp+80]:a  |           
  ;;    stack:   |[rbp-16]:a  |[rbp-32]:a
  0x4002BD0F   183   L4:   nop                                                [90]
  0x4002BD10   184         mov       rax, [rbp + 8]                           [48 8B 45 08]
  0x4002BD14   188         addq      rax, 0xF8                                [48 83 C0 F8]
  0x4002BD18   192         mov       rdi, [rsp + 16]                          [48 8B 7C 24 10]
  0x4002BD1D   197         call      rax <template_call>                      [FF D0]
  ;; reg-ref-map: {}
  ;; frame-ref-map: rbp+80 {14}
  ;; at test.output.HelloWorld.main(HelloWorld.java:29) [bci: 5]
  ;;             |0           |1          
  ;;    locals:  |[rbp+80]:a  |           
  ;;    stack:   |[rbp-16]:j  |[rbp-32]:j
  0x4002BD1F   199         nop                                                [90]
  ;; -------------------- 8: return ---------------------------------------------------------------------
  0x4002BD20   200         addq      rbp, 0x40                                [48 83 C5 40]
  0x4002BD24   204         leave                                              [C9]
  0x4002BD25   205         ret       0x10                                     [C2 10 00]
   <|@
end_nmethod
begin_bytecodes
  public static void test.output.HelloWorld.main(java.lang.String[])
  Stack=2, Locals=1
  [29]   0: getstatic java.lang.System.out:PrintStream | 178 0 2
  [29]   3: ldc "Hello World!" | 18 3
  [29]   5: invokevirtual java.io.PrintStream.println(String):void | 182 0 4
  [30]   8: return | 177
  LineNumberTable:
    line 29: 0
    line 30: 8
  LocalVariableTable:
    Start Length Slot Name               Descriptor            Generic-signature
    0     9      0    args               [Ljava/lang/String;   
   <|@
end_bytecodes
